rtl/accelerator/fir_accelerator.sv
module fir_accelerator (
    input  logic        clk,
    input  logic        reset,

    input  logic        write_en,
    input  logic        read_en,

    input  logic [4:0]  address,
    input  logic [31:0] write_data,

    output logic [31:0] read_data,
    output logic        done
);

    logic signed [31:0] sample_in;

    logic signed [31:0] coeff0;
    logic signed [31:0] coeff1;
    logic signed [31:0] coeff2;
    logic signed [31:0] coeff3;

    logic signed [31:0] delay0;
    logic signed [31:0] delay1;
    logic signed [31:0] delay2;

    logic signed [63:0] product0;
    logic signed [63:0] product1;
    logic signed [63:0] product2;
    logic signed [63:0] product3;

    logic signed [63:0] accumulator;

    logic signed [31:0] result;


    // ========================================
    // MULTIPLICATION
    // ========================================

    always_comb begin

        product0 = sample_in * coeff0;
        product1 = delay0    * coeff1;
        product2 = delay1    * coeff2;
        product3 = delay2    * coeff3;

        accumulator =
            product0 +
            product1 +
            product2 +
            product3;

    end


    // ========================================
    // REGISTER WRITES
    // ========================================

    always_ff @(posedge clk) begin

        if (reset) begin

            sample_in <= 32'sd0;

            coeff0 <= 32'sd0;
            coeff1 <= 32'sd0;
            coeff2 <= 32'sd0;
            coeff3 <= 32'sd0;

            delay0 <= 32'sd0;
            delay1 <= 32'sd0;
            delay2 <= 32'sd0;

            result <= 32'sd0;

            done <= 1'b0;

        end

        else begin

            done <= 1'b0;

            if (write_en) begin

                case (address)

                    // INPUT
                    5'h00:
                        sample_in <= $signed(write_data);

                    // COEFF0
                    5'h04:
                        coeff0 <= $signed(write_data);

                    // COEFF1
                    5'h08:
                        coeff1 <= $signed(write_data);

                    // COEFF2
                    5'h0C:
                        coeff2 <= $signed(write_data);

                    // COEFF3
                    5'h10:
                        coeff3 <= $signed(write_data);

                    // CONTROL
                    5'h14: begin

                        if (write_data[0]) begin

                            result <= accumulator[31:0];

                            delay2 <= delay1;
                            delay1 <= delay0;
                            delay0 <= sample_in;

                            done <= 1'b1;

                        end

                    end

                    default: begin
                    end

                endcase

            end

        end

    end


    // ========================================
    // REGISTER READS
    // ========================================

    always_comb begin

        read_data = 32'd0;

        if (read_en) begin

            case (address)

                // INPUT
                5'h00:
                    read_data = sample_in;

                // COEFF0
                5'h04:
                    read_data = coeff0;

                // COEFF1
                5'h08:
                    read_data = coeff1;

                // COEFF2
                5'h0C:
                    read_data = coeff2;

                // COEFF3
                5'h10:
                    read_data = coeff3;

                // RESULT
                5'h18:
                    read_data = result;

                // STATUS
                5'h1C:
                    read_data = {31'd0, done};

                default:
                    read_data = 32'd0;

            endcase

        end

    end

endmodule

rtl/memory/data_memory.sv
module data_memory (
    input  logic        clk,
    input  logic        mem_write,
    input  logic [31:0] address,
    input  logic [31:0] write_data,

    output logic [31:0] read_data
);

    // 256 words × 32 bits = 1 KB
    logic [31:0] memory [0:255];

    // Synchronous write
    always_ff @(posedge clk) begin
        if (mem_write)
            memory[address[9:2]] <= write_data;
    end

    // Asynchronous read
    always_comb begin
        read_data = memory[address[9:2]];
    end

endmodule

rtl/bus/mmio_interconnect.sv
module mmio_interconnect (
    input  logic        clk,
    input  logic        reset,

    input  logic        mem_write,
    input  logic        mem_read,

    input  logic [31:0] address,
    input  logic [31:0] write_data,

    output logic [31:0] read_data,

    output logic        fir_selected,
    output logic        fir_done
);

    logic is_fir;

    logic [31:0] ram_read_data;
    logic [31:0] fir_read_data;

    logic ram_write_en;
    logic fir_write_en;
    logic fir_read_en;


    // ========================================
    // ADDRESS MAP
    // ========================================
    //
    // Normal RAM:
    //   0x0000_0000 ...
    //
    // FIR MMIO region:
    //   0x4000_0000 - 0x4000_FFFF
    //
    // ========================================

    assign is_fir =
        (address[31:16] == 16'h4000);

    assign fir_selected = is_fir;


    // ========================================
    // WRITE / READ ENABLE ROUTING
    // ========================================

    assign ram_write_en =
        mem_write && !is_fir;

    assign fir_write_en =
        mem_write && is_fir;

    assign fir_read_en =
        mem_read && is_fir;


    // ========================================
    // NORMAL DATA RAM
    // ========================================

    data_memory ram (
        .clk(clk),

        .mem_write(ram_write_en),

        .address(address),
        .write_data(write_data),

        .read_data(ram_read_data)
    );


    // ========================================
    // FIR ACCELERATOR
    // ========================================

    fir_accelerator fir (
        .clk(clk),
        .reset(reset),

        .write_en(fir_write_en),
        .read_en(fir_read_en),

        // FIR only needs the local register offset
        .address(address[4:0]),

        .write_data(write_data),

        .read_data(fir_read_data),

        .done(fir_done)
    );


    // ========================================
    // READ DATA MUX
    // ========================================

    always_comb begin

        if (is_fir)
            read_data = fir_read_data;

        else
            read_data = ram_read_data;

    end

endmodule

rtl/cpu/alu.sv
module alu (
    input  logic [31:0] a,
    input  logic [31:0] b,
    input  logic [3:0]  alu_ctrl,

    output logic [31:0] result,
    output logic        zero
);

    always_comb begin

        case (alu_ctrl)

            4'b0000: result = a + b;                    // ADD
            4'b0001: result = a - b;                    // SUB
            4'b0010: result = a & b;                    // AND
            4'b0011: result = a | b;                    // OR
            4'b0100: result = a ^ b;                    // XOR

            4'b0101: result = a << b[4:0];              // SLL
            4'b0110: result = a >> b[4:0];              // SRL
            4'b0111: result = $signed(a) >>> b[4:0];    // SRA

            4'b1000: result =
                ($signed(a) < $signed(b)) ? 32'd1 : 32'd0; // SLT

            4'b1001: result =
                (a < b) ? 32'd1 : 32'd0;                   // SLTU

            default: result = 32'd0;

        endcase

    end

    assign zero = (result == 32'd0);

endmodule

rtl/cpu/regfile.sv
module regfile (
    input  logic        clk,
    input  logic        we,

    input  logic [4:0]  rs1_addr,
    input  logic [4:0]  rs2_addr,
    input  logic [4:0]  rd_addr,

    input  logic [31:0] rd_data,

    output logic [31:0] rs1_data,
    output logic [31:0] rs2_data
);

    // 32 registers, each 32 bits wide
    logic [31:0] registers [0:31];

    // Synchronous write
    always_ff @(posedge clk) begin
        if (we && (rd_addr != 5'd0))
            registers[rd_addr] <= rd_data;
    end

    // Asynchronous reads
    always_comb begin
        rs1_data = (rs1_addr == 5'd0)
                 ? 32'd0
                 : registers[rs1_addr];

        rs2_data = (rs2_addr == 5'd0)
                 ? 32'd0
                 : registers[rs2_addr];
    end

endmodule

rtl/cpu/datapath.sv
module datapath (
    input  logic        clk,
    input  logic        reset,

    input  logic        we,

    input  logic        mem_write,
    input  logic        mem_to_reg,

    input  logic        jump,
    input  logic        lui,

    input  logic [31:0] pc_plus_4,

    input  logic [4:0]  rs1_addr,
    input  logic [4:0]  rs2_addr,
    input  logic [4:0]  rd_addr,

    input  logic [31:0] immediate,

    input  logic        alu_src,
    input  logic [3:0]  alu_ctrl,

    output logic [31:0] rs1_data,
    output logic [31:0] rs2_data,

    output logic [31:0] alu_result,
    output logic [31:0] mem_read_data,

    output logic        zero,

    output logic        fir_selected,
    output logic        fir_done
);

    logic [31:0] alu_b;
    logic [31:0] writeback_data;


    regfile rf (
        .clk(clk),
        .we(we),

        .rs1_addr(rs1_addr),
        .rs2_addr(rs2_addr),

        .rd_addr(rd_addr),
        .rd_data(writeback_data),

        .rs1_data(rs1_data),
        .rs2_data(rs2_data)
    );


    assign alu_b =
        alu_src ? immediate : rs2_data;


    alu alu_unit (
        .a(rs1_data),
        .b(alu_b),

        .alu_ctrl(alu_ctrl),

        .result(alu_result),
        .zero(zero)
    );


    mmio_interconnect mmio (
        .clk(clk),
        .reset(reset),

        .mem_write(mem_write),
        .mem_read(mem_to_reg),

        .address(alu_result),
        .write_data(rs2_data),

        .read_data(mem_read_data),

        .fir_selected(fir_selected),
        .fir_done(fir_done)
    );


    always_comb begin

        if (jump)
            writeback_data = pc_plus_4;

        else if (lui)
            writeback_data = immediate;

        else if (mem_to_reg)
            writeback_data = mem_read_data;

        else
            writeback_data = alu_result;

    end

endmodule

rtl/cpu/decoder.sv
module decoder (
    input  logic [31:0] instruction,

    output logic [4:0]  rs1_addr,
    output logic [4:0]  rs2_addr,
    output logic [4:0]  rd_addr,

    output logic [31:0] immediate,

    output logic        alu_src,
    output logic        reg_write,
    output logic        mem_write,
    output logic        mem_to_reg,

    output logic [1:0]  branch_type,
    output logic        jump,
    output logic        lui,

    output logic [3:0]  alu_ctrl
);

    logic [6:0] opcode;
    logic [2:0] funct3;
    logic [6:0] funct7;

    assign opcode   = instruction[6:0];
    assign rd_addr  = instruction[11:7];
    assign funct3   = instruction[14:12];
    assign rs1_addr = instruction[19:15];
    assign rs2_addr = instruction[24:20];
    assign funct7   = instruction[31:25];

    always_comb begin

        immediate   = 32'd0;
        alu_src     = 1'b0;
        reg_write   = 1'b0;
        mem_write   = 1'b0;
        mem_to_reg  = 1'b0;
        branch_type = 2'b00;
        jump        = 1'b0;
        lui         = 1'b0;
        alu_ctrl    = 4'b0000;

        case (opcode)

            // R-Type
            7'b0110011: begin
                reg_write = 1'b1;

                case (funct3)

                    3'b000: begin
                        if (funct7 == 7'b0100000)
                            alu_ctrl = 4'b0001; // SUB
                        else
                            alu_ctrl = 4'b0000; // ADD
                    end

                    3'b111:
                        alu_ctrl = 4'b0010; // AND

                    3'b110:
                        alu_ctrl = 4'b0011; // OR

                    3'b100:
                        alu_ctrl = 4'b0100; // XOR

                    3'b001:
                        alu_ctrl = 4'b0101; // SLL

                    3'b101: begin
                        if (funct7 == 7'b0100000)
                            alu_ctrl = 4'b0111; // SRA
                        else
                            alu_ctrl = 4'b0110; // SRL
                    end

                    3'b010:
                        alu_ctrl = 4'b1000; // SLT

                    3'b011:
                        alu_ctrl = 4'b1001; // SLTU

                    default:
                        alu_ctrl = 4'b0000;

                endcase
            end


            // ADDI
            7'b0010011: begin

                reg_write = 1'b1;
                alu_src   = 1'b1;

                immediate = {
                    {20{instruction[31]}},
                    instruction[31:20]
                };

                alu_ctrl = 4'b0000;
            end


            // LW
            7'b0000011: begin

                reg_write  = 1'b1;
                alu_src    = 1'b1;
                mem_to_reg = 1'b1;

                immediate = {
                    {20{instruction[31]}},
                    instruction[31:20]
                };

                alu_ctrl = 4'b0000;
            end


            // SW
            7'b0100011: begin

                alu_src   = 1'b1;
                mem_write = 1'b1;

                immediate = {
                    {20{instruction[31]}},
                    instruction[31:25],
                    instruction[11:7]
                };

                alu_ctrl = 4'b0000;
            end


            // BEQ / BNE
            7'b1100011: begin

                alu_ctrl = 4'b0001;

                immediate = {
                    {19{instruction[31]}},
                    instruction[31],
                    instruction[7],
                    instruction[30:25],
                    instruction[11:8],
                    1'b0
                };

                case (funct3)

                    3'b000:
                        branch_type = 2'b01; // BEQ

                    3'b001:
                        branch_type = 2'b10; // BNE

                    default:
                        branch_type = 2'b00;

                endcase
            end


            // JAL
            7'b1101111: begin

                reg_write = 1'b1;
                jump      = 1'b1;

                immediate = {
                    {11{instruction[31]}},
                    instruction[31],
                    instruction[19:12],
                    instruction[20],
                    instruction[30:21],
                    1'b0
                };
            end


            // LUI
            7'b0110111: begin

                reg_write = 1'b1;
                lui       = 1'b1;

                immediate = {
                    instruction[31:12],
                    12'b0
                };

            end


            default: begin
                immediate   = 32'd0;
                alu_src     = 1'b0;
                reg_write   = 1'b0;
                mem_write   = 1'b0;
                mem_to_reg  = 1'b0;
                branch_type = 2'b00;
                jump        = 1'b0;
                lui         = 1'b0;
                alu_ctrl    = 4'b0000;
            end

        endcase
    end

endmodule

rtl/cpu/cpu_core.sv
module cpu_core (
    input  logic        clk,
    input  logic        reset,

    input  logic [31:0] instruction,
    input  logic [31:0] pc_plus_4,

    output logic [31:0] alu_result,

    output logic [1:0]  branch_type,
    output logic        jump,

    output logic        zero,
    output logic [31:0] immediate,

    output logic        fir_selected,
    output logic        fir_done
);

    logic [4:0] rs1_addr;
    logic [4:0] rs2_addr;
    logic [4:0] rd_addr;

    logic alu_src;
    logic reg_write;
    logic mem_write;
    logic mem_to_reg;
    logic lui;

    logic [3:0] alu_ctrl;

    logic [31:0] rs1_data;
    logic [31:0] rs2_data;
    logic [31:0] mem_read_data;


    decoder dec (
        .instruction(instruction),

        .rs1_addr(rs1_addr),
        .rs2_addr(rs2_addr),
        .rd_addr(rd_addr),

        .immediate(immediate),

        .alu_src(alu_src),
        .reg_write(reg_write),

        .mem_write(mem_write),
        .mem_to_reg(mem_to_reg),

        .branch_type(branch_type),

        .jump(jump),
        .lui(lui),

        .alu_ctrl(alu_ctrl)
    );


    datapath dp (
        .clk(clk),
        .reset(reset),

        .we(reg_write),

        .mem_write(mem_write),
        .mem_to_reg(mem_to_reg),

        .jump(jump),
        .lui(lui),

        .pc_plus_4(pc_plus_4),

        .rs1_addr(rs1_addr),
        .rs2_addr(rs2_addr),
        .rd_addr(rd_addr),

        .immediate(immediate),

        .alu_src(alu_src),
        .alu_ctrl(alu_ctrl),

        .rs1_data(rs1_data),
        .rs2_data(rs2_data),

        .alu_result(alu_result),
        .mem_read_data(mem_read_data),

        .zero(zero),

        .fir_selected(fir_selected),
        .fir_done(fir_done)
    );

endmodule

rtl/memory/instruction_memory.sv
module instruction_memory (
    input  logic [31:0] address,
    output logic [31:0] instruction
);

    logic [31:0] memory [0:255];

    initial begin
        $readmemh("programs/loop.hex", memory);
    end

    assign instruction = memory[address[9:2]];

endmodule

rtl/cpu/pc.sv
module pc (
    input  logic        clk,
    input  logic        reset,

    input  logic        branch_taken,
    input  logic [31:0] branch_target,

    input  logic        jump,
    input  logic [31:0] jump_target,

    output logic [31:0] pc_out
);

    always_ff @(posedge clk) begin

        if (reset)
            pc_out <= 32'd0;

        else if (jump)
            pc_out <= jump_target;

        else if (branch_taken)
            pc_out <= branch_target;

        else
            pc_out <= pc_out + 32'd4;

    end

endmodule

rtl/cpu/riscv_cpu.sv
module riscv_cpu (
    input  logic        clk,
    input  logic        reset,

    output logic [31:0] pc,

    output logic [31:0] instruction,

    output logic [31:0] alu_result,

    output logic        fir_selected,
    output logic        fir_done
);

    logic [1:0] branch_type;

    logic zero;
    logic jump;

    logic [31:0] immediate;

    logic branch_taken;

    logic [31:0] branch_target;
    logic [31:0] jump_target;

    logic [31:0] pc_plus_4;


    // ========================================
    // PC CALCULATIONS
    // ========================================

    assign pc_plus_4 =
        pc + 32'd4;

    assign branch_target =
        pc + immediate;

    assign jump_target =
        pc + immediate;


    // ========================================
    // BRANCH DECISION
    // ========================================

    always_comb begin

        case (branch_type)

            // BEQ
            2'b01:
                branch_taken = zero;

            // BNE
            2'b10:
                branch_taken = !zero;

            default:
                branch_taken = 1'b0;

        endcase

    end


    // ========================================
    // PROGRAM COUNTER
    // ========================================

    pc pc_unit (
        .clk(clk),
        .reset(reset),

        .branch_taken(branch_taken),
        .branch_target(branch_target),

        .jump(jump),
        .jump_target(jump_target),

        .pc_out(pc)
    );


    // ========================================
    // INSTRUCTION MEMORY
    // ========================================

    instruction_memory imem (
        .address(pc),
        .instruction(instruction)
    );


    // ========================================
    // CPU CORE
    // ========================================

    cpu_core core (
        .clk(clk),
        .reset(reset),

        .instruction(instruction),

        .pc_plus_4(pc_plus_4),

        .alu_result(alu_result),

        .branch_type(branch_type),

        .jump(jump),

        .zero(zero),

        .immediate(immediate),

        .fir_selected(fir_selected),
        .fir_done(fir_done)
    );

endmodule

tb/tb_soc_waveform.sv
module tb_soc_waveform;

    logic clk;
    logic reset;

    logic [31:0] pc;
    logic [31:0] instruction;
    logic [31:0] alu_result;

    logic fir_selected;
    logic fir_done;

    riscv_cpu dut (
        .clk(clk),
        .reset(reset),

        .pc(pc),
        .instruction(instruction),
        .alu_result(alu_result),

        .fir_selected(fir_selected),
        .fir_done(fir_done)
    );


    initial begin
        clk = 1'b0;
        forever #5 clk = ~clk;
    end


    initial begin

        $dumpfile("soc_waveform.vcd");
        $dumpvars(0, tb_soc_waveform);

        reset = 1'b1;

        repeat (2)
            @(posedge clk);

        reset = 1'b0;

        repeat (40)
            @(posedge clk);

        $finish;

    end

endmodule

soc_waveform.vcd
$version Generated by VerilatedVcd $end
$timescale 1ps $end
 $scope module $rootio $end
 $upscope $end
 $scope module tb_soc_waveform $end
  $var wire 1 y clk $end
  $var wire 1 z reset $end
  $var wire 32 # pc [31:0] $end
  $var wire 32 $ instruction [31:0] $end
  $var wire 32 % alu_result [31:0] $end
  $var wire 1 & fir_selected $end
  $var wire 1 ' fir_done $end
  $scope module dut $end
   $var wire 1 y clk $end
   $var wire 1 z reset $end
   $var wire 32 # pc [31:0] $end
   $var wire 32 $ instruction [31:0] $end
   $var wire 32 % alu_result [31:0] $end
   $var wire 1 & fir_selected $end
   $var wire 1 ' fir_done $end
   $var wire 2 ( branch_type [1:0] $end
   $var wire 1 ) zero $end
   $var wire 1 * jump $end
   $var wire 32 + immediate [31:0] $end
   $var wire 1 , branch_taken $end
   $var wire 32 - branch_target [31:0] $end
   $var wire 32 - jump_target [31:0] $end
   $var wire 32 . pc_plus_4 [31:0] $end
   $scope module core $end
    $var wire 1 y clk $end
    $var wire 1 z reset $end
    $var wire 32 $ instruction [31:0] $end
    $var wire 32 . pc_plus_4 [31:0] $end
    $var wire 32 % alu_result [31:0] $end
    $var wire 2 ( branch_type [1:0] $end
    $var wire 1 * jump $end
    $var wire 1 ) zero $end
    $var wire 32 + immediate [31:0] $end
    $var wire 1 & fir_selected $end
    $var wire 1 ' fir_done $end
    $var wire 5 / rs1_addr [4:0] $end
    $var wire 5 0 rs2_addr [4:0] $end
    $var wire 5 1 rd_addr [4:0] $end
    $var wire 1 2 alu_src $end
    $var wire 1 3 reg_write $end
    $var wire 1 4 mem_write $end
    $var wire 1 5 mem_to_reg $end
    $var wire 1 6 lui $end
    $var wire 4 7 alu_ctrl [3:0] $end
    $var wire 32 8 rs1_data [31:0] $end
    $var wire 32 9 rs2_data [31:0] $end
    $var wire 32 : mem_read_data [31:0] $end
    $scope module dec $end
     $var wire 32 $ instruction [31:0] $end
     $var wire 5 / rs1_addr [4:0] $end
     $var wire 5 0 rs2_addr [4:0] $end
     $var wire 5 1 rd_addr [4:0] $end
     $var wire 32 + immediate [31:0] $end
     $var wire 1 2 alu_src $end
     $var wire 1 3 reg_write $end
     $var wire 1 4 mem_write $end
     $var wire 1 5 mem_to_reg $end
     $var wire 2 ( branch_type [1:0] $end
     $var wire 1 * jump $end
     $var wire 1 6 lui $end
     $var wire 4 7 alu_ctrl [3:0] $end
     $var wire 7 ; opcode [6:0] $end
     $var wire 3 < funct3 [2:0] $end
     $var wire 7 = funct7 [6:0] $end
    $upscope $end
    $scope module dp $end
     $var wire 1 y clk $end
     $var wire 1 z reset $end
     $var wire 1 3 we $end
     $var wire 1 4 mem_write $end
     $var wire 1 5 mem_to_reg $end
     $var wire 1 * jump $end
     $var wire 1 6 lui $end
     $var wire 32 . pc_plus_4 [31:0] $end
     $var wire 5 / rs1_addr [4:0] $end
     $var wire 5 0 rs2_addr [4:0] $end
     $var wire 5 1 rd_addr [4:0] $end
     $var wire 32 + immediate [31:0] $end
     $var wire 1 2 alu_src $end
     $var wire 4 7 alu_ctrl [3:0] $end
     $var wire 32 8 rs1_data [31:0] $end
     $var wire 32 9 rs2_data [31:0] $end
     $var wire 32 % alu_result [31:0] $end
     $var wire 32 : mem_read_data [31:0] $end
     $var wire 1 ) zero $end
     $var wire 1 & fir_selected $end
     $var wire 1 ' fir_done $end
     $var wire 32 > alu_b [31:0] $end
     $var wire 32 ? writeback_data [31:0] $end
     $scope module alu_unit $end
      $var wire 32 8 a [31:0] $end
      $var wire 32 > b [31:0] $end
      $var wire 4 7 alu_ctrl [3:0] $end
      $var wire 32 % result [31:0] $end
      $var wire 1 ) zero $end
     $upscope $end
     $scope module mmio $end
      $var wire 1 y clk $end
      $var wire 1 z reset $end
      $var wire 1 4 mem_write $end
      $var wire 1 5 mem_read $end
      $var wire 32 % address [31:0] $end
      $var wire 32 9 write_data [31:0] $end
      $var wire 32 : read_data [31:0] $end
      $var wire 1 & fir_selected $end
      $var wire 1 ' fir_done $end
      $var wire 1 & is_fir $end
      $var wire 32 @ ram_read_data [31:0] $end
      $var wire 32 A fir_read_data [31:0] $end
      $var wire 1 B ram_write_en $end
      $var wire 1 C fir_write_en $end
      $var wire 1 D fir_read_en $end
      $scope module fir $end
       $var wire 1 y clk $end
       $var wire 1 z reset $end
       $var wire 1 C write_en $end
       $var wire 1 D read_en $end
       $var wire 5 E address [4:0] $end
       $var wire 32 9 write_data [31:0] $end
       $var wire 32 A read_data [31:0] $end
       $var wire 1 ' done $end
       $var wire 32 F sample_in [31:0] $end
       $var wire 32 G coeff0 [31:0] $end
       $var wire 32 H coeff1 [31:0] $end
       $var wire 32 I coeff2 [31:0] $end
       $var wire 32 J coeff3 [31:0] $end
       $var wire 32 K delay0 [31:0] $end
       $var wire 32 L delay1 [31:0] $end
       $var wire 32 M delay2 [31:0] $end
       $var wire 64 N product0 [63:0] $end
       $var wire 64 P product1 [63:0] $end
       $var wire 64 R product2 [63:0] $end
       $var wire 64 T product3 [63:0] $end
       $var wire 64 V accumulator [63:0] $end
       $var wire 32 X result [31:0] $end
      $upscope $end
      $scope module ram $end
       $var wire 1 y clk $end
       $var wire 1 B mem_write $end
       $var wire 32 % address [31:0] $end
       $var wire 32 9 write_data [31:0] $end
       $var wire 32 @ read_data [31:0] $end
      $upscope $end
     $upscope $end
     $scope module rf $end
      $var wire 1 y clk $end
      $var wire 1 3 we $end
      $var wire 5 / rs1_addr [4:0] $end
      $var wire 5 0 rs2_addr [4:0] $end
      $var wire 5 1 rd_addr [4:0] $end
      $var wire 32 ? rd_data [31:0] $end
      $var wire 32 8 rs1_data [31:0] $end
      $var wire 32 9 rs2_data [31:0] $end
      $var wire 32 Y registers[0] [31:0] $end
      $var wire 32 Z registers[1] [31:0] $end
      $var wire 32 [ registers[2] [31:0] $end
      $var wire 32 \ registers[3] [31:0] $end
      $var wire 32 ] registers[4] [31:0] $end
      $var wire 32 ^ registers[5] [31:0] $end
      $var wire 32 _ registers[6] [31:0] $end
      $var wire 32 ` registers[7] [31:0] $end
      $var wire 32 a registers[8] [31:0] $end
      $var wire 32 b registers[9] [31:0] $end
      $var wire 32 c registers[10] [31:0] $end
      $var wire 32 d registers[11] [31:0] $end
      $var wire 32 e registers[12] [31:0] $end
      $var wire 32 f registers[13] [31:0] $end
      $var wire 32 g registers[14] [31:0] $end
      $var wire 32 h registers[15] [31:0] $end
      $var wire 32 i registers[16] [31:0] $end
      $var wire 32 j registers[17] [31:0] $end
      $var wire 32 k registers[18] [31:0] $end
      $var wire 32 l registers[19] [31:0] $end
      $var wire 32 m registers[20] [31:0] $end
      $var wire 32 n registers[21] [31:0] $end
      $var wire 32 o registers[22] [31:0] $end
      $var wire 32 p registers[23] [31:0] $end
      $var wire 32 q registers[24] [31:0] $end
      $var wire 32 r registers[25] [31:0] $end
      $var wire 32 s registers[26] [31:0] $end
      $var wire 32 t registers[27] [31:0] $end
      $var wire 32 u registers[28] [31:0] $end
      $var wire 32 v registers[29] [31:0] $end
      $var wire 32 w registers[30] [31:0] $end
      $var wire 32 x registers[31] [31:0] $end
     $upscope $end
    $upscope $end
   $upscope $end
   $scope module imem $end
    $var wire 32 # address [31:0] $end
    $var wire 32 $ instruction [31:0] $end
   $upscope $end
   $scope module pc_unit $end
    $var wire 1 y clk $end
    $var wire 1 z reset $end
    $var wire 1 , branch_taken $end
    $var wire 32 - branch_target [31:0] $end
    $var wire 1 * jump $end
    $var wire 32 - jump_target [31:0] $end
    $var wire 32 # pc_out [31:0] $end
   $upscope $end
  $upscope $end
 $upscope $end
$enddefinitions $end


#0
b00000000000000000000000000000000 #
b01000000000000000000010100110111 $
b00000000000000000000000000000000 %
0&
0'
b00 (
1)
0*
b01000000000000000000000000000000 +
0,
b01000000000000000000000000000000 -
b00000000000000000000000000000100 .
b00000 /
b00000 0
b01010 1
02
13
04
05
16
b0000 7
b00000000000000000000000000000000 8
b00000000000000000000000000000000 9
b00000000000000000000000000000000 :
b0110111 ;
b000 <
b0100000 =
b00000000000000000000000000000000 >
b01000000000000000000000000000000 ?
b00000000000000000000000000000000 @
b00000000000000000000000000000000 A
0B
0C
0D
b00000 E
b00000000000000000000000000000000 F
b00000000000000000000000000000000 G
b00000000000000000000000000000000 H
b00000000000000000000000000000000 I
b00000000000000000000000000000000 J
b00000000000000000000000000000000 K
b00000000000000000000000000000000 L
b00000000000000000000000000000000 M
b0000000000000000000000000000000000000000000000000000000000000000 N
b0000000000000000000000000000000000000000000000000000000000000000 P
b0000000000000000000000000000000000000000000000000000000000000000 R
b0000000000000000000000000000000000000000000000000000000000000000 T
b0000000000000000000000000000000000000000000000000000000000000000 V
b00000000000000000000000000000000 X
b00000000000000000000000000000000 Y
b00000000000000000000000000000000 Z
b00000000000000000000000000000000 [
b00000000000000000000000000000000 \
b00000000000000000000000000000000 ]
b00000000000000000000000000000000 ^
b00000000000000000000000000000000 _
b00000000000000000000000000000000 `
b00000000000000000000000000000000 a
b00000000000000000000000000000000 b
b00000000000000000000000000000000 c
b00000000000000000000000000000000 d
b00000000000000000000000000000000 e
b00000000000000000000000000000000 f
b00000000000000000000000000000000 g
b00000000000000000000000000000000 h
b00000000000000000000000000000000 i
b00000000000000000000000000000000 j
b00000000000000000000000000000000 k
b00000000000000000000000000000000 l
b00000000000000000000000000000000 m
b00000000000000000000000000000000 n
b00000000000000000000000000000000 o
b00000000000000000000000000000000 p
b00000000000000000000000000000000 q
b00000000000000000000000000000000 r
b00000000000000000000000000000000 s
b00000000000000000000000000000000 t
b00000000000000000000000000000000 u
b00000000000000000000000000000000 v
b00000000000000000000000000000000 w
b00000000000000000000000000000000 x
0y
1z
#5
b01000000000000000000000000000000 c
1y
#10
0y
#15
b00000000000000000000000000000100 #
b00000000000100000000001010010011 $
b00000000000000000000000000000001 %
0)
b00000000000000000000000000000001 +
b00000000000000000000000000000101 -
b00000000000000000000000000001000 .
b00001 0
b00101 1
12
06
b0010011 ;
b0000000 =
b00000000000000000000000000000001 >
b00000000000000000000000000000001 ?
b00001 E
1y
0z
#20
0y
#25
b00000000000000000000000000001000 #
b00000000010101010010001000100011 $
b01000000000000000000000000000100 %
1&
b00000000000000000000000000000100 +
b00000000000000000000000000001100 -
b00000000000000000000000000001100 .
b01010 /
b00101 0
b00100 1
03
14
b01000000000000000000000000000000 8
b00000000000000000000000000000001 9
b0100011 ;
b010 <
b00000000000000000000000000000100 >
b01000000000000000000000000000100 ?
1C
b00100 E
b00000000000000000000000000000001 ^
1y
#30
0y
#35
b00000000000000000000000000001100 #
b00000000001000000000001010010011 $
b00000000000000000000000000000010 %
0&
b00000000000000000000000000000010 +
b00000000000000000000000000001110 -
b00000000000000000000000000010000 .
b00000 /
b00010 0
b00101 1
13
04
b00000000000000000000000000000000 8
b00000000000000000000000000000000 9
b0010011 ;
b000 <
b00000000000000000000000000000010 >
b00000000000000000000000000000010 ?
0C
b00010 E
b00000000000000000000000000000001 G
1y
#40
0y
#45
b00000000000000000000000000010000 #
b00000000010101010010010000100011 $
b01000000000000000000000000001000 %
1&
b00000000000000000000000000001000 +
b00000000000000000000000000011000 -
b00000000000000000000000000010100 .
b01010 /
b00101 0
b01000 1
03
14
b01000000000000000000000000000000 8
b00000000000000000000000000000010 9
b0100011 ;
b010 <
b00000000000000000000000000001000 >
b01000000000000000000000000001000 ?
1C
b01000 E
b00000000000000000000000000000010 ^
1y
#50
0y
#55
b00000000000000000000000000010100 #
b00000000001100000000001010010011 $
b00000000000000000000000000000011 %
0&
b00000000000000000000000000000011 +
b00000000000000000000000000010111 -
b00000000000000000000000000011000 .
b00000 /
b00011 0
b00101 1
13
04
b00000000000000000000000000000000 8
b00000000000000000000000000000000 9
b0010011 ;
b000 <
b00000000000000000000000000000011 >
b00000000000000000000000000000011 ?
0C
b00011 E
b00000000000000000000000000000010 H
1y
#60
0y
#65
b00000000000000000000000000011000 #
b00000000010101010010011000100011 $
b01000000000000000000000000001100 %
1&
b00000000000000000000000000001100 +
b00000000000000000000000000100100 -
b00000000000000000000000000011100 .
b01010 /
b00101 0
b01100 1
03
14
b01000000000000000000000000000000 8
b00000000000000000000000000000011 9
b0100011 ;
b010 <
b00000000000000000000000000001100 >
b01000000000000000000000000001100 ?
1C
b01100 E
b00000000000000000000000000000011 ^
1y
#70
0y
#75
b00000000000000000000000000011100 #
b00000000010000000000001010010011 $
b00000000000000000000000000000100 %
0&
b00000000000000000000000000000100 +
b00000000000000000000000000100000 -
b00000000000000000000000000100000 .
b00000 /
b00100 0
b00101 1
13
04
b00000000000000000000000000000000 8
b00000000000000000000000000000000 9
b0010011 ;
b000 <
b00000000000000000000000000000100 >
b00000000000000000000000000000100 ?
0C
b00100 E
b00000000000000000000000000000011 I
1y
#80
0y
#85
b00000000000000000000000000100000 #
b00000000010101010010100000100011 $
b01000000000000000000000000010000 %
1&
b00000000000000000000000000010000 +
b00000000000000000000000000110000 -
b00000000000000000000000000100100 .
b01010 /
b00101 0
b10000 1
03
14
b01000000000000000000000000000000 8
b00000000000000000000000000000100 9
b0100011 ;
b010 <
b00000000000000000000000000010000 >
b01000000000000000000000000010000 ?
1C
b10000 E
b00000000000000000000000000000100 ^
1y
#90
0y
#95
b00000000000000000000000000100100 #
b00000000101000000000001010010011 $
b00000000000000000000000000001010 %
0&
b00000000000000000000000000001010 +
b00000000000000000000000000101110 -
b00000000000000000000000000101000 .
b00000 /
b01010 0
b00101 1
13
04
b00000000000000000000000000000000 8
b01000000000000000000000000000000 9
b0010011 ;
b000 <
b00000000000000000000000000001010 >
b00000000000000000000000000001010 ?
0C
b01010 E
b00000000000000000000000000000100 J
1y
#100
0y
